xiaoyi/xiaoyi.py
xiaoyi-0.1.2.dist-info/licenses/LICENSE
xiaoyi-0.1.2.dist-info/METADATA
xiaoyi-0.1.2.dist-info/WHEEL
xiaoyi-0.1.2.dist-info/entry_points.txt
xiaoyi-0.1.2.dist-info/top_level.txt
xiaoyi-0.1.2.dist-info/RECORD
