Metadata-Version: 2.4
Name: xiaoyi
Version: 0.1.2
Summary: Xiaoyi 小易编程语言
Author-email: liuzhongyi <lqvsyi@sina.com>
License: Apache-2.0
Project-URL: Homepage, https://gitee.com/LZY4/xiaoyi
Project-URL: Source, https://github.com/cnlnr/xiaoyi
Project-URL: Tracker, https://gitee.com/LZY4/xiaoyi/issues
Keywords: 小易,xiaoyi,编程语言,CLI,中文编程
License-File: LICENSE
Requires-Dist: libcst
Requires-Dist: regex
Dynamic: license-file
